index/__init__.py
index/cli.py
index/agent/agent.py
index/agent/message_manager.py
index/agent/models.py
index/agent/prompts.py
index/agent/utils.py
index/agent/demo_images/complex_layout_highlight.png
index/agent/demo_images/complex_layout_small_elements.png
index/agent/demo_images/loading.png
index/agent/demo_images/scroll.png
index/browser/browser.py
index/browser/detector.py
index/browser/findVisibleInteractiveElements.js
index/browser/models.py
index/browser/utils.py
index/browser/fonts/OpenSans-Medium.ttf
index/controller/controller.py
index/controller/default_actions.py
index/llm/llm.py
index/llm/providers/__init__.py
index/llm/providers/anthropic.py
index/llm/providers/anthropic_bedrock.py
index/llm/providers/gemini.py
index/llm/providers/gemini_vertex.py
index/llm/providers/groq.py
index/llm/providers/openai.py
lmnr_index-0.1.13.dist-info/METADATA
lmnr_index-0.1.13.dist-info/WHEEL
lmnr_index-0.1.13.dist-info/entry_points.txt
lmnr_index-0.1.13.dist-info/licenses/LICENSE
lmnr_index-0.1.13.dist-info/RECORD
