Metadata-Version: 2.4
Name: lmnr-index
Version: 0.1.13
Summary: Index - SOTA browser AI agent for autonomous task execution on the web
License:                                  Apache License
License-File: LICENSE
Requires-Python: >=3.10
Requires-Dist: anthropic[bedrock]>=0.52.0
Requires-Dist: backoff>=2.2.1
Requires-Dist: docstring-parser>=0.16
Requires-Dist: google-genai>=1.11.0
Requires-Dist: groq>=0.24.0
Requires-Dist: lmnr[anthropic,groq,openai]>=0.6.2
Requires-Dist: openai>=1.65.2
Requires-Dist: pillow>=11.1.0
Requires-Dist: playwright>=1.50.0
Requires-Dist: rich>=13.5.0
Requires-Dist: tenacity>=9.0.0
Requires-Dist: textual>=0.50.1
Requires-Dist: typer>=0.9.0
